aiopynoon/__init__.py
aiopynoon/const.py
aiopynoon/entity.py
aiopynoon/event.py
aiopynoon/exceptions.py
aiopynoon/line.py
aiopynoon/noon.py
aiopynoon/scene.py
aiopynoon/space.py
aiopynoon-0.0.2.dist-info/LICENSE.txt
aiopynoon-0.0.2.dist-info/METADATA
aiopynoon-0.0.2.dist-info/WHEEL
aiopynoon-0.0.2.dist-info/top_level.txt
aiopynoon-0.0.2.dist-info/RECORD
