Metadata-Version: 2.1
Name: aiopynoon
Version: 0.0.2
Summary: Async Python library for Noon Home
Home-page: http://github.com/alistairg/aiopynoon
Author: Alistair Galbraith
Author-email: github@alistairs.net
License: MIT
Platform: UNKNOWN
Classifier: Development Status :: 3 - Alpha
Classifier: License :: OSI Approved :: MIT License
Classifier: Operating System :: OS Independent
Classifier: Programming Language :: Python
Classifier: Programming Language :: Python :: 3.7
Classifier: Topic :: Home Automation
Classifier: Topic :: Software Development :: Libraries :: Python Modules
Requires-Dist: aiohttp
